gutmetrics/__init__.py
gutmetrics/analysis/__init__.py
gutmetrics/analysis/classification.py
gutmetrics/analysis/correlation.py
gutmetrics/analysis/regression.py
gutmetrics/preprocessing/__init__.py
gutmetrics/preprocessing/cleaning.py
gutmetrics/preprocessing/scaling.py
gutmetrics/utils/__init__.py
gutmetrics/utils/stats.py
gutmetrics/visualization/__init__.py
gutmetrics/visualization/heatmaps.py
gutmetrics/visualization/plots.py
gutmetrics-0.1.3.dist-info/LICENSE
gutmetrics-0.1.3.dist-info/METADATA
gutmetrics-0.1.3.dist-info/WHEEL
gutmetrics-0.1.3.dist-info/RECORD
